{
  "conference": "ICML",
  "year": 2023,
  "track": "Conference",
  "focus_country": "India",
  "focus_country_code": "IN",
  "generated_at": "2025-07-07T15:54:11.289493",
  "globalStats": {
    "totalPapers": 2397,
    "totalAuthors": 6579,
    "totalCountries": 43,
    "countries": [
      {
        "affiliation_country": "US",
        "paper_count": 1049,
        "author_count": 2769,
        "spotlights": 0,
        "orals": 97
      },
      {
        "affiliation_country": "CN",
        "paper_count": 389,
        "author_count": 1116,
        "spotlights": 0,
        "orals": 20
      },
      {
        "affiliation_country": "GB",
        "paper_count": 160,
        "author_count": 400,
        "spotlights": 0,
        "orals": 22
      },
      {
        "affiliation_country": "DE",
        "paper_count": 103,
        "author_count": 208,
        "spotlights": 0,
        "orals": 8
      },
      {
        "affiliation_country": "KR",
        "paper_count": 98,
        "author_count": 257,
        "spotlights": 0,
        "orals": 10
      },
      {
        "affiliation_country": "CA",
        "paper_count": 88,
        "author_count": 187,
        "spotlights": 0,
        "orals": 13
      },
      {
        "affiliation_country": "FR",
        "paper_count": 80,
        "author_count": 173,
        "spotlights": 0,
        "orals": 6
      },
      {
        "affiliation_country": "CH",
        "paper_count": 68,
        "author_count": 117,
        "spotlights": 0,
        "orals": 9
      },
      {
        "affiliation_country": "SG",
        "paper_count": 47,
        "author_count": 102,
        "spotlights": 0,
        "orals": 1
      },
      {
        "affiliation_country": "IL",
        "paper_count": 47,
        "author_count": 78,
        "spotlights": 0,
        "orals": 5
      },
      {
        "affiliation_country": "JP",
        "paper_count": 44,
        "author_count": 90,
        "spotlights": 0,
        "orals": 3
      },
      {
        "affiliation_country": "AU",
        "paper_count": 38,
        "author_count": 70,
        "spotlights": 0,
        "orals": 4
      },
      {
        "affiliation_country": "NL",
        "paper_count": 27,
        "author_count": 49,
        "spotlights": 0,
        "orals": 2
      },
      {
        "affiliation_country": "IT",
        "paper_count": 24,
        "author_count": 47,
        "spotlights": 0,
        "orals": 1
      },
      {
        "affiliation_country": "SE",
        "paper_count": 13,
        "author_count": 29,
        "spotlights": 0,
        "orals": 0
      },
      {
        "affiliation_country": "IN",
        "paper_count": 13,
        "author_count": 32,
        "spotlights": 0,
        "orals": 2
      },
      {
        "affiliation_country": "BE",
        "paper_count": 13,
        "author_count": 29,
        "spotlights": 0,
        "orals": 1
      },
      {
        "affiliation_country": "RU",
        "paper_count": 12,
        "author_count": 31,
        "spotlights": 0,
        "orals": 2
      },
      {
        "affiliation_country": "UNK",
        "paper_count": 11,
        "author_count": 19,
        "spotlights": 0,
        "orals": 2
      },
      {
        "affiliation_country": "AT",
        "paper_count": 11,
        "author_count": 20,
        "spotlights": 0,
        "orals": 2
      },
      {
        "affiliation_country": "FI",
        "paper_count": 10,
        "author_count": 25,
        "spotlights": 0,
        "orals": 1
      },
      {
        "affiliation_country": "DK",
        "paper_count": 9,
        "author_count": 16,
        "spotlights": 0,
        "orals": 1
      },
      {
        "affiliation_country": "AE",
        "paper_count": 6,
        "author_count": 10,
        "spotlights": 0,
        "orals": 0
      },
      {
        "affiliation_country": "ES",
        "paper_count": 6,
        "author_count": 14,
        "spotlights": 0,
        "orals": 1
      },
      {
        "affiliation_country": "SA",
        "paper_count": 6,
        "author_count": 9,
        "spotlights": 0,
        "orals": 0
      },
      {
        "affiliation_country": "NO",
        "paper_count": 3,
        "author_count": 3,
        "spotlights": 0,
        "orals": 0
      },
      {
        "affiliation_country": "LU",
        "paper_count": 3,
        "author_count": 6,
        "spotlights": 0,
        "orals": 0
      },
      {
        "affiliation_country": "PL",
        "paper_count": 2,
        "author_count": 3,
        "spotlights": 0,
        "orals": 0
      },
      {
        "affiliation_country": "GR",
        "paper_count": 2,
        "author_count": 2,
        "spotlights": 0,
        "orals": 0
      },
      {
        "affiliation_country": "CZ",
        "paper_count": 2,
        "author_count": 2,
        "spotlights": 0,
        "orals": 0
      },
      {
        "affiliation_country": "VN",
        "paper_count": 1,
        "author_count": 2,
        "spotlights": 0,
        "orals": 0
      },
      {
        "affiliation_country": "UNK",
        "paper_count": 1,
        "author_count": 1,
        "spotlights": 0,
        "orals": 0
      },
      {
        "affiliation_country": "RO",
        "paper_count": 1,
        "author_count": 1,
        "spotlights": 0,
        "orals": 1
      },
      {
        "affiliation_country": "PT",
        "paper_count": 1,
        "author_count": 1,
        "spotlights": 0,
        "orals": 0
      },
      {
        "affiliation_country": "NZ",
        "paper_count": 1,
        "author_count": 1,
        "spotlights": 0,
        "orals": 0
      },
      {
        "affiliation_country": "IE",
        "paper_count": 1,
        "author_count": 1,
        "spotlights": 0,
        "orals": 0
      },
      {
        "affiliation_country": "IR",
        "paper_count": 1,
        "author_count": 4,
        "spotlights": 0,
        "orals": 0
      },
      {
        "affiliation_country": "HU",
        "paper_count": 1,
        "author_count": 2,
        "spotlights": 0,
        "orals": 0
      },
      {
        "affiliation_country": "EE",
        "paper_count": 1,
        "author_count": 1,
        "spotlights": 0,
        "orals": 0
      },
      {
        "affiliation_country": "CL",
        "paper_count": 1,
        "author_count": 4,
        "spotlights": 0,
        "orals": 0
      },
      {
        "affiliation_country": "BD",
        "paper_count": 1,
        "author_count": 1,
        "spotlights": 0,
        "orals": 1
      },
      {
        "affiliation_country": "AM",
        "paper_count": 1,
        "author_count": 1,
        "spotlights": 0,
        "orals": 0
      },
      {
        "affiliation_country": "AR",
        "paper_count": 1,
        "author_count": 1,
        "spotlights": 0,
        "orals": 0
      }
    ]
  },
  "focusCountrySummary": {
    "country": "India",
    "country_code": "IN",
    "rank": 16,
    "paper_count": 13,
    "author_count": 32,
    "percentage": 0.54,
    "spotlights": 0,
    "orals": 2,
    "institution_count": 12,
    "academic_institutions": 10,
    "corporate_institutions": 2
  },
  "focusCountry": {
    "authorship": {
      "at_least_one": {
        "count": 13,
        "papers": [
          {
            "id": "3MlWDiBcpr",
            "title": "Discrete Continuous Optimization Framework for Simultaneous Clustering and Training in Mixture Models",
            "isSpotlight": false,
            "isOral": false
          },
          {
            "id": "6vauERTFMb",
            "title": "StriderNet: A Graph Reinforcement Learning Approach to Optimize Atomic Structures on Rough Energy Landscapes",
            "isSpotlight": false,
            "isOral": false
          },
          {
            "id": "Aev7tepsqx",
            "title": "Diffusion Models as Artists: Are we Closing the Gap between Humans and Machines?",
            "isSpotlight": false,
            "isOral": true
          },
          {
            "id": "MXfTQp8bZF",
            "title": "Which Tricks are Important for Learning to Rank?",
            "isSpotlight": false,
            "isOral": false
          },
          {
            "id": "R7X1sTaM6J",
            "title": "Conditional Tree Matching for Inference-Time Adaptation of Tree Prediction Models",
            "isSpotlight": false,
            "isOral": false
          },
          {
            "id": "Tw7pgl861K",
            "title": "Off-Policy Average Reward Actor-Critic with Deterministic Policy Search",
            "isSpotlight": false,
            "isOral": false
          },
          {
            "id": "bpRTAnJ8LW",
            "title": "Pythia: A Suite for Analyzing Large Language Models Across Training and Scaling",
            "isSpotlight": false,
            "isOral": true
          },
          {
            "id": "jTcRlAAO01",
            "title": "Principled Offline RL in the Presence of Rich Exogenous Information",
            "isSpotlight": false,
            "isOral": false
          },
          {
            "id": "kwb6T6LP7f",
            "title": "SemSup-XC: Semantic Supervision for Zero and Few-shot Extreme Classification",
            "isSpotlight": false,
            "isOral": false
          },
          {
            "id": "oJANAXYc18",
            "title": "Deep Regression Unlearning",
            "isSpotlight": false,
            "isOral": false
          },
          {
            "id": "oqkckmjCYp",
            "title": "Interval Bound Interpolation for Few-shot Learning with Few Tasks",
            "isSpotlight": false,
            "isOral": false
          },
          {
            "id": "pNi4q28UyI",
            "title": "GRAFENNE: Learning on Graphs with Heterogeneous and Dynamic Feature Sets",
            "isSpotlight": false,
            "isOral": false
          },
          {
            "id": "wVGreJ2338",
            "title": "Featured Graph Coarsening with Similarity Guarantees",
            "isSpotlight": false,
            "isOral": false
          }
        ]
      },
      "majority": {
        "count": 7,
        "papers": [
          {
            "id": "3MlWDiBcpr",
            "title": "Discrete Continuous Optimization Framework for Simultaneous Clustering and Training in Mixture Models",
            "isSpotlight": false,
            "isOral": false
          },
          {
            "id": "6vauERTFMb",
            "title": "StriderNet: A Graph Reinforcement Learning Approach to Optimize Atomic Structures on Rough Energy Landscapes",
            "isSpotlight": false,
            "isOral": false
          },
          {
            "id": "R7X1sTaM6J",
            "title": "Conditional Tree Matching for Inference-Time Adaptation of Tree Prediction Models",
            "isSpotlight": false,
            "isOral": false
          },
          {
            "id": "Tw7pgl861K",
            "title": "Off-Policy Average Reward Actor-Critic with Deterministic Policy Search",
            "isSpotlight": false,
            "isOral": false
          },
          {
            "id": "oqkckmjCYp",
            "title": "Interval Bound Interpolation for Few-shot Learning with Few Tasks",
            "isSpotlight": false,
            "isOral": false
          },
          {
            "id": "pNi4q28UyI",
            "title": "GRAFENNE: Learning on Graphs with Heterogeneous and Dynamic Feature Sets",
            "isSpotlight": false,
            "isOral": false
          },
          {
            "id": "wVGreJ2338",
            "title": "Featured Graph Coarsening with Similarity Guarantees",
            "isSpotlight": false,
            "isOral": false
          }
        ]
      },
      "first_author": {
        "count": 9,
        "papers": [
          {
            "id": "3MlWDiBcpr",
            "title": "Discrete Continuous Optimization Framework for Simultaneous Clustering and Training in Mixture Models",
            "isSpotlight": false,
            "isOral": false
          },
          {
            "id": "6vauERTFMb",
            "title": "StriderNet: A Graph Reinforcement Learning Approach to Optimize Atomic Structures on Rough Energy Landscapes",
            "isSpotlight": false,
            "isOral": false
          },
          {
            "id": "R7X1sTaM6J",
            "title": "Conditional Tree Matching for Inference-Time Adaptation of Tree Prediction Models",
            "isSpotlight": false,
            "isOral": false
          },
          {
            "id": "Tw7pgl861K",
            "title": "Off-Policy Average Reward Actor-Critic with Deterministic Policy Search",
            "isSpotlight": false,
            "isOral": false
          },
          {
            "id": "kwb6T6LP7f",
            "title": "SemSup-XC: Semantic Supervision for Zero and Few-shot Extreme Classification",
            "isSpotlight": false,
            "isOral": false
          },
          {
            "id": "oJANAXYc18",
            "title": "Deep Regression Unlearning",
            "isSpotlight": false,
            "isOral": false
          },
          {
            "id": "oqkckmjCYp",
            "title": "Interval Bound Interpolation for Few-shot Learning with Few Tasks",
            "isSpotlight": false,
            "isOral": false
          },
          {
            "id": "pNi4q28UyI",
            "title": "GRAFENNE: Learning on Graphs with Heterogeneous and Dynamic Feature Sets",
            "isSpotlight": false,
            "isOral": false
          },
          {
            "id": "wVGreJ2338",
            "title": "Featured Graph Coarsening with Similarity Guarantees",
            "isSpotlight": false,
            "isOral": false
          }
        ]
      }
    },
    "institutions": [
      {
        "institute": "Indian Institute of Technology Delhi",
        "total_paper_count": 4,
        "unique_paper_count": 4,
        "author_count": 10,
        "spotlights": 0,
        "orals": 0,
        "type": "academic",
        "papers": [
          {
            "id": "6vauERTFMb",
            "title": "StriderNet: A Graph Reinforcement Learning Approach to Optimize Atomic Structures on Rough Energy Landscapes",
            "isSpotlight": false,
            "isOral": false
          },
          {
            "id": "pNi4q28UyI",
            "title": "GRAFENNE: Learning on Graphs with Heterogeneous and Dynamic Feature Sets",
            "isSpotlight": false,
            "isOral": false
          },
          {
            "id": "kwb6T6LP7f",
            "title": "SemSup-XC: Semantic Supervision for Zero and Few-shot Extreme Classification",
            "isSpotlight": false,
            "isOral": false
          },
          {
            "id": "wVGreJ2338",
            "title": "Featured Graph Coarsening with Similarity Guarantees",
            "isSpotlight": false,
            "isOral": false
          }
        ],
        "authors": [
          "Vaibhav Bihani",
          "Sahil Manchanda",
          "Sayan Ranu",
          "N M Anoop Krishnan",
          "Pranjal Aggarwal",
          "Shubham Gupta",
          "Manoj Kumar",
          "Anurag Sharma",
          "Shashwat Saxena",
          "Sandeep Kumar"
        ]
      },
      {
        "institute": "Indian Institute of Technology Bombay",
        "total_paper_count": 2,
        "unique_paper_count": 2,
        "author_count": 7,
        "spotlights": 0,
        "orals": 0,
        "type": "academic",
        "papers": [
          {
            "id": "3MlWDiBcpr",
            "title": "Discrete Continuous Optimization Framework for Simultaneous Clustering and Training in Mixture Models",
            "isSpotlight": false,
            "isOral": false
          },
          {
            "id": "R7X1sTaM6J",
            "title": "Conditional Tree Matching for Inference-Time Adaptation of Tree Prediction Models",
            "isSpotlight": false,
            "isOral": false
          }
        ],
        "authors": [
          "Parth Vipul Sangani",
          "Arjun Shashank Kashettiwar",
          "Pritish Chakraborty",
          "Durga S",
          "Harshit Varma",
          "Abhijeet Awasthi",
          "Sunita Sarawagi"
        ]
      },
      {
        "institute": "Microsoft",
        "total_paper_count": 1,
        "unique_paper_count": 1,
        "author_count": 1,
        "spotlights": 0,
        "orals": 0,
        "type": "corporate",
        "papers": [
          {
            "id": "3MlWDiBcpr",
            "title": "Discrete Continuous Optimization Framework for Simultaneous Clustering and Training in Mixture Models",
            "isSpotlight": false,
            "isOral": false
          }
        ],
        "authors": [
          "Bhuvan Reddy Gangula"
        ]
      },
      {
        "institute": "Jawaharlal Nehru Centre for Advanced Scientific Research",
        "total_paper_count": 1,
        "unique_paper_count": 1,
        "author_count": 1,
        "spotlights": 0,
        "orals": 0,
        "type": "corporate",
        "papers": [
          {
            "id": "6vauERTFMb",
            "title": "StriderNet: A Graph Reinforcement Learning Approach to Optimize Atomic Structures on Rough Energy Landscapes",
            "isSpotlight": false,
            "isOral": false
          }
        ],
        "authors": [
          "Srikanth Sastry"
        ]
      },
      {
        "institute": "Universidad de Alicante",
        "total_paper_count": 1,
        "unique_paper_count": 1,
        "author_count": 1,
        "spotlights": 0,
        "orals": 1,
        "type": "academic",
        "papers": [
          {
            "id": "Aev7tepsqx",
            "title": "Diffusion Models as Artists: Are we Closing the Gap between Humans and Machines?",
            "isSpotlight": false,
            "isOral": true
          }
        ],
        "authors": [
          "Akash Nagaraj"
        ]
      },
      {
        "institute": "ShareChat",
        "total_paper_count": 1,
        "unique_paper_count": 1,
        "author_count": 1,
        "spotlights": 0,
        "orals": 0,
        "type": "academic",
        "papers": [
          {
            "id": "MXfTQp8bZF",
            "title": "Which Tricks are Important for Learning to Rank?",
            "isSpotlight": false,
            "isOral": false
          }
        ],
        "authors": [
          "Aleksei Ustimenko"
        ]
      },
      {
        "institute": "Indian Institute of Science",
        "total_paper_count": 1,
        "unique_paper_count": 1,
        "author_count": 4,
        "spotlights": 0,
        "orals": 0,
        "type": "academic",
        "papers": [
          {
            "id": "Tw7pgl861K",
            "title": "Off-Policy Average Reward Actor-Critic with Deterministic Policy Search",
            "isSpotlight": false,
            "isOral": false
          }
        ],
        "authors": [
          "Naman Saxena",
          "Subhojyoti Khastagir",
          "Shishir N Y",
          "Shalabh Bhatnagar"
        ]
      },
      {
        "institute": "Indraprastha Institute of Information Technology",
        "total_paper_count": 1,
        "unique_paper_count": 1,
        "author_count": 1,
        "spotlights": 0,
        "orals": 1,
        "type": "academic",
        "papers": [
          {
            "id": "bpRTAnJ8LW",
            "title": "Pythia: A Suite for Analyzing Large Language Models Across Training and Scaling",
            "isSpotlight": false,
            "isOral": true
          }
        ],
        "authors": [
          "Mohammad Aflah Khan"
        ]
      },
      {
        "institute": "Matrusri Engineering College",
        "total_paper_count": 1,
        "unique_paper_count": 1,
        "author_count": 1,
        "spotlights": 0,
        "orals": 1,
        "type": "academic",
        "papers": [
          {
            "id": "bpRTAnJ8LW",
            "title": "Pythia: A Suite for Analyzing Large Language Models Across Training and Scaling",
            "isSpotlight": false,
            "isOral": true
          }
        ],
        "authors": [
          "Shivanshu Purohit"
        ]
      },
      {
        "institute": "Manipal Institute of Technology",
        "total_paper_count": 1,
        "unique_paper_count": 1,
        "author_count": 1,
        "spotlights": 0,
        "orals": 0,
        "type": "academic",
        "papers": [
          {
            "id": "jTcRlAAO01",
            "title": "Principled Offline RL in the Presence of Rich Exogenous Information",
            "isSpotlight": false,
            "isOral": false
          }
        ],
        "authors": [
          "Yonathan Efroni"
        ]
      },
      {
        "institute": "Kalinga Institute of Industrial Technology",
        "total_paper_count": 1,
        "unique_paper_count": 1,
        "author_count": 1,
        "spotlights": 0,
        "orals": 0,
        "type": "academic",
        "papers": [
          {
            "id": "oJANAXYc18",
            "title": "Deep Regression Unlearning",
            "isSpotlight": false,
            "isOral": false
          }
        ],
        "authors": [
          "Ayush Kumar Tarun"
        ]
      },
      {
        "institute": "Indian Statistical Institute",
        "total_paper_count": 1,
        "unique_paper_count": 1,
        "author_count": 3,
        "spotlights": 0,
        "orals": 0,
        "type": "academic",
        "papers": [
          {
            "id": "oqkckmjCYp",
            "title": "Interval Bound Interpolation for Few-shot Learning with Few Tasks",
            "isSpotlight": false,
            "isOral": false
          }
        ],
        "authors": [
          "Shounak Datta",
          "Anish Chakrabarty",
          "Swagatam Das"
        ]
      }
    ]
  },
  "institutions": {
    "summary": {
      "total_institutions": 0,
      "academic_institutions": 0,
      "corporate_institutions": 0,
      "total_papers": 0,
      "total_authors": 0,
      "avg_papers_per_institution": 0,
      "avg_authors_per_institution": 0
    },
    "top_institutions": [],
    "total_institutions": 0
  },
  "config": {
    "focus_country_code": "IN",
    "focus_country_name": "India",
    "colors": {
      "us": "hsl(221, 83%, 53%)",
      "cn": "hsl(0, 84%, 60%)",
      "focusCountry": "hsl(36, 96%, 50%)",
      "primary": "hsl(var(--primary))",
      "secondary": "hsl(var(--secondary-foreground))",
      "academic": "hsl(221, 83%, 53%)",
      "corporate": "hsl(330, 80%, 60%)",
      "rest": "hsl(330, 60%, 30%)",
      "spotlight": "hsl(48, 96%, 50%)",
      "oral": "hsl(142, 71%, 45%)",
      "papers": "hsl(200, 65%, 50%)",
      "authors": "hsl(280, 55%, 55%)",
      "US": "hsl(221, 83%, 53%)",
      "CN": "hsl(0, 84%, 60%)",
      "GB": "hsl(120, 70%, 45%)",
      "HK": "hsl(300, 75%, 50%)",
      "SG": "hsl(180, 80%, 50%)",
      "CA": "hsl(15, 85%, 55%)",
      "DE": "hsl(45, 90%, 50%)",
      "KR": "hsl(270, 75%, 50%)",
      "FR": "hsl(240, 80%, 55%)",
      "CH": "hsl(135, 70%, 45%)",
      "UK": "hsl(90, 65%, 50%)",
      "AU": "hsl(315, 80%, 55%)",
      "JP": "hsl(195, 85%, 50%)",
      "UNK": "hsl(0, 0%, 60%)",
      "IL": "hsl(210, 75%, 50%)",
      "IT": "hsl(105, 70%, 50%)",
      "NL": "hsl(255, 80%, 55%)",
      "AE": "hsl(30, 85%, 55%)",
      "TW": "hsl(165, 75%, 50%)",
      "AI": "hsl(285, 80%, 55%)",
      "IN": "hsl(36, 96%, 50%)",
      "AT": "hsl(60, 85%, 50%)",
      "RU": "hsl(330, 75%, 50%)",
      "DK": "hsl(225, 80%, 55%)",
      "SE": "hsl(75, 70%, 50%)",
      "SA": "hsl(345, 85%, 55%)",
      "BE": "hsl(150, 75%, 50%)",
      "ES": "hsl(300, 70%, 50%)",
      "FI": "hsl(120, 80%, 45%)",
      "MO": "hsl(270, 85%, 55%)",
      "GR": "hsl(195, 75%, 50%)",
      "VN": "hsl(45, 80%, 55%)",
      "BR": "hsl(105, 85%, 50%)",
      "PL": "hsl(315, 75%, 50%)",
      "CZ": "hsl(165, 80%, 50%)",
      "NO": "hsl(240, 75%, 55%)",
      "CL": "hsl(285, 70%, 50%)",
      "TR": "hsl(15, 80%, 55%)",
      "PT": "hsl(135, 75%, 50%)",
      "EU": "hsl(210, 85%, 50%)",
      "BG": "hsl(75, 80%, 50%)",
      "LU": "hsl(330, 80%, 55%)",
      "IR": "hsl(180, 75%, 50%)",
      "NZ": "hsl(255, 85%, 55%)",
      "PH": "hsl(60, 75%, 50%)",
      "ZW": "hsl(120, 70%, 50%)",
      "IE": "hsl(345, 80%, 55%)",
      "CX": "hsl(195, 80%, 50%)",
      "MY": "hsl(270, 75%, 55%)",
      "CO": "hsl(30, 80%, 55%)",
      "KP": "hsl(150, 80%, 50%)",
      "SI": "hsl(285, 75%, 50%)",
      "AC": "hsl(45, 85%, 55%)",
      "TH": "hsl(105, 80%, 50%)",
      "RE": "hsl(315, 85%, 55%)",
      "UY": "hsl(165, 75%, 50%)",
      "AM": "hsl(240, 80%, 55%)",
      "IO": "hsl(75, 85%, 50%)",
      "CY": "hsl(330, 75%, 50%)",
      "TD": "hsl(195, 75%, 55%)",
      "NA": "hsl(255, 80%, 50%)",
      "HR": "hsl(60, 80%, 55%)",
      "EG": "hsl(120, 85%, 45%)"
    }
  },
  "dashboard": {
    "summary": {
      "title": "Research Impact Overview",
      "content": [
        "India contributed 13 research papers to ICML 2023, representing 0.5% of the conference's total accepted works and ranking 16 globally among contributing nations.",
        "India researchers demonstrated strong research leadership with 69.2% of papers featuring India first authors, indicating significant intellectual contribution to the global machine learning discourse.",
        "The research quality is evidenced by a 0.0% spotlight acceptance rate, with 0 paper(s) receiving this prestigious recognition among the conference's most impactful contributions.",
        "India's machine learning ecosystem comprises 32 unique researchers across 12 institutions, with a balanced representation of 10 academic institutions and 2 corporate research entities."
      ]
    },
    "context": {
      "title": "Global Research Landscape",
      "content": [
        "The global research landscape is led by the United States (43.8% of papers) and China (16.2%), followed by the United Kingdom (6.7%) and Germany (4.3%), with India contributing 0.5% of total research output.",
        "India ranks 16 globally in research volume, positioning it as an emerging contributor in the international machine learning research ecosystem with substantial growth potential.",
        "Within the Asia-Pacific region, India trails China, South Korea, Singapore, and Hong Kong in absolute research contributions, highlighting opportunities for enhanced regional collaboration and capacity building."
      ],
      "subtitle": "India's position within the international machine learning research community and comparative analysis with leading nations."
    },
    "focusCountry": {
      "title": "India Research Ecosystem Analysis",
      "content": [
        "India researchers exhibit strong research independence with 53.8% of papers having majority India authorship, indicating substantial domestic research capacity and reduced dependence on international collaboration.",
        "The 69.2% first authorship rate demonstrates India researchers' leadership in conceptualizing and driving research projects, reflecting growing confidence and expertise in the field.",
        "With 32 unique authors contributing across 13 papers, India maintains an efficient author-to-paper ratio of 0.41, suggesting productive individual contributions and effective research mentorship."
      ],
      "subtitle": "Detailed examination of authorship patterns, collaboration dynamics, and research leadership within India's machine learning community."
    },
    "institutions": {
      "title": "Institutional Research Excellence",
      "content": [
        "The Unknown emerges as the national leader with 0 papers and 0 authors, including the country's 0 spotlight papers, demonstrating exceptional research quality and productivity.",
        "Academic institutions dominate India's research landscape with 83.3% representation (10 of 12 institutions), while corporate research centers contribute 16.7%, indicating strong university-led research culture.",
        "The institutional diversity spans premier engineering institutes (IITs), specialized research universities (IISc), and corporate R&D centers, creating a robust ecosystem for sustained machine learning research growth."
      ],
      "subtitle": "Comprehensive evaluation of India's academic and corporate institutions contributing to machine learning research excellence."
    }
  }
}